[{"text":"We're ","ticks":9629,"offset":35610.24889822836,"event_offsets":[{"offset":35610.24889822836,"char_count":6}]},{"text":"We're ","ticks":9629,"offset":35610.24889822836,"event_offsets":[{"offset":35610.24889822836,"char_count":6}]},{"text":"We're talking talking talking aaaway ","ticks":9629,"offset":35610.24889822836,"event_offsets":[{"offset":35610.24889822836,"char_count":6},{"offset":36142.793902002886,"char_count":8},{"offset":36142.793902002886,"char_count":8},{"offset":36142.793902002886,"char_count":8},{"offset":36501.52213371211,"char_count":1},{"offset":36501.52213371211,"char_count":1},{"offset":36501.52213371211,"char_count":1},{"offset":36682.73536416316,"char_count":4}]},{"text":"way ","ticks":9919,"offset":36682.73536416316,"event_offsets":[{"offset":36682.73536416316,"char_count":0},{"offset":36682.73536416316,"char_count":4}]},{"text":"way ","ticks":9919,"offset":36682.73536416316,"event_offsets":[{"offset":36682.73536416316,"char_count":0},{"offset":36682.73536416316,"char_count":4}]},{"text":"I ","ticks":9919,"offset":36682.73536416316,"event_offsets":[{"offset":36682.73536416316,"char_count":0},{"offset":38461.58360593779,"char_count":2}]},{"text":"I ","ticks":10400,"offset":38461.58360593779,"event_offsets":[{"offset":38461.58360593779,"char_count":2}]},{"text":"I don't don't don't know know know what ","ticks":10400,"offset":38461.58360593779,"event_offsets":[{"offset":38461.58360593779,"char_count":2},{"offset":38635.40037800308,"char_count":6},{"offset":38635.40037800308,"char_count":6},{"offset":38635.40037800308,"char_count":6},{"offset":38990.430380519436,"char_count":5},{"offset":38990.430380519436,"char_count":5},{"offset":38990.430380519436,"char_count":5},{"offset":39349.15861222866,"char_count":5}]},{"text":"what ","ticks":10640,"offset":39349.15861222866,"event_offsets":[{"offset":39349.15861222866,"char_count":0},{"offset":39349.15861222866,"char_count":5}]},{"text":"what ","ticks":10640,"offset":39349.15861222866,"event_offsets":[{"offset":39349.15861222866,"char_count":0},{"offset":39349.15861222866,"char_count":5}]},{"text":"I'm ","ticks":10640,"offset":39349.15861222866,"event_offsets":[{"offset":39349.15861222866,"char_count":0},{"offset":40059.21861726136,"char_count":4}]},{"text":"I'm ","ticks":10832,"offset":40059.21861726136,"event_offsets":[{"offset":40059.21861726136,"char_count":4}]},{"text":"I'm to to to say say say I'll I'll I'll say say say it it it aaanynynyway ","ticks":10832,"offset":40059.21861726136,"event_offsets":[{"offset":40059.21861726136,"char_count":4},{"offset":40417.94684897058,"char_count":3},{"offset":40417.94684897058,"char_count":3},{"offset":40417.94684897058,"char_count":3},{"offset":40599.160079421636,"char_count":4},{"offset":40599.160079421636,"char_count":4},{"offset":40599.160079421636,"char_count":4},{"offset":40954.19008193799,"char_count":5},{"offset":40954.19008193799,"char_count":5},{"offset":40954.19008193799,"char_count":5},{"offset":41309.22008445433,"char_count":4},{"offset":41309.22008445433,"char_count":4},{"offset":41309.22008445433,"char_count":4},{"offset":41841.76508822886,"char_count":3},{"offset":41841.76508822886,"char_count":3},{"offset":41841.76508822886,"char_count":3},{"offset":42022.97831867991,"char_count":1},{"offset":42022.97831867991,"char_count":1},{"offset":42022.97831867991,"char_count":1},{"offset":42196.79509074521,"char_count":2},{"offset":42196.79509074521,"char_count":2},{"offset":42196.79509074521,"char_count":2},{"offset":42551.825093261556,"char_count":4}]},{"text":"way ","ticks":11506,"offset":42551.825093261556,"event_offsets":[{"offset":42551.825093261556,"char_count":0},{"offset":42551.825093261556,"char_count":4}]},{"text":"way ","ticks":11506,"offset":42551.825093261556,"event_offsets":[{"offset":42551.825093261556,"char_count":0},{"offset":42551.825093261556,"char_count":4}]},{"text":"To","ticks":11506,"offset":42551.825093261556,"event_offsets":[{"offset":42551.825093261556,"char_count":0},{"offset":44156.85656297088,"char_count":2}]},{"text":"To","ticks":11940,"offset":44156.85656297088,"event_offsets":[{"offset":44156.85656297088,"char_count":2}]},{"text":"Today's day's day's aaanononother ther ther day day day to to to find find find you ","ticks":11940,"offset":44156.85656297088,"event_offsets":[{"offset":44156.85656297088,"char_count":2},{"offset":44334.371564229055,"char_count":6},{"offset":44334.371564229055,"char_count":6},{"offset":44334.371564229055,"char_count":6},{"offset":44689.40156674541,"char_count":1},{"offset":44689.40156674541,"char_count":1},{"offset":44689.40156674541,"char_count":1},{"offset":45048.12979845463,"char_count":2},{"offset":45048.12979845463,"char_count":2},{"offset":45048.12979845463,"char_count":2},{"offset":45403.159800970985,"char_count":5},{"offset":45403.159800970985,"char_count":5},{"offset":45403.159800970985,"char_count":5},{"offset":45758.18980348733,"char_count":4},{"offset":45758.18980348733,"char_count":4},{"offset":45758.18980348733,"char_count":4},{"offset":46113.21980600368,"char_count":3},{"offset":46113.21980600368,"char_count":3},{"offset":46113.21980600368,"char_count":3},{"offset":46298.131265647615,"char_count":5},{"offset":46298.131265647615,"char_count":5},{"offset":46298.131265647615,"char_count":5},{"offset":46653.16126816396,"char_count":4}]},{"text":"you ","ticks":12615,"offset":46653.16126816396,"event_offsets":[{"offset":46653.16126816396,"char_count":0},{"offset":46653.16126816396,"char_count":4}]},{"text":"you ","ticks":12615,"offset":46653.16126816396,"event_offsets":[{"offset":46653.16126816396,"char_count":0},{"offset":46653.16126816396,"char_count":4}]},{"text":"Shy","ticks":12615,"offset":46653.16126816396,"event_offsets":[{"offset":46653.16126816396,"char_count":0},{"offset":47363.22127319666,"char_count":3}]},{"text":"Shy","ticks":12807,"offset":47363.22127319666,"event_offsets":[{"offset":47363.22127319666,"char_count":3}]},{"text":"Shying ing ing aaaway ","ticks":12807,"offset":47363.22127319666,"event_offsets":[{"offset":47363.22127319666,"char_count":3},{"offset":47895.76627697118,"char_count":4},{"offset":47895.76627697118,"char_count":4},{"offset":47895.76627697118,"char_count":4},{"offset":48076.979507422235,"char_count":1},{"offset":48076.979507422235,"char_count":1},{"offset":48076.979507422235,"char_count":1},{"offset":48250.796279487535,"char_count":4}]},{"text":"way ","ticks":13047,"offset":48250.796279487535,"event_offsets":[{"offset":48250.796279487535,"char_count":0},{"offset":48250.796279487535,"char_count":4}]},{"text":"way ","ticks":13047,"offset":48250.796279487535,"event_offsets":[{"offset":48250.796279487535,"char_count":0},{"offset":48250.796279487535,"char_count":4}]},{"text":"I'll ","ticks":13047,"offset":48250.796279487535,"event_offsets":[{"offset":48250.796279487535,"char_count":0},{"offset":50214.55598090609,"char_count":5}]},{"text":"I'll ","ticks":13578,"offset":50214.55598090609,"event_offsets":[{"offset":50214.55598090609,"char_count":5}]},{"text":"I'll be be be cococoming ming ming for for for your your your lololove, ve, ve, OK? ","ticks":13578,"offset":50214.55598090609,"event_offsets":[{"offset":50214.55598090609,"char_count":5},{"offset":50388.37275297138,"char_count":3},{"offset":50388.37275297138,"char_count":3},{"offset":50388.37275297138,"char_count":3},{"offset":50569.58598342243,"char_count":2},{"offset":50569.58598342243,"char_count":2},{"offset":50569.58598342243,"char_count":2},{"offset":50743.40275548773,"char_count":5},{"offset":50743.40275548773,"char_count":5},{"offset":50743.40275548773,"char_count":5},{"offset":50924.615985938784,"char_count":4},{"offset":50924.615985938784,"char_count":4},{"offset":50924.615985938784,"char_count":4},{"offset":51098.43275800408,"char_count":5},{"offset":51098.43275800408,"char_count":5},{"offset":51098.43275800408,"char_count":5},{"offset":51279.64598845513,"char_count":2},{"offset":51279.64598845513,"char_count":2},{"offset":51279.64598845513,"char_count":2},{"offset":51457.16098971331,"char_count":4},{"offset":51457.16098971331,"char_count":4},{"offset":51457.16098971331,"char_count":4},{"offset":51812.190992229655,"char_count":4}]},{"text":"OK? ","ticks":14010,"offset":51812.190992229655,"event_offsets":[{"offset":51812.190992229655,"char_count":0},{"offset":51812.190992229655,"char_count":4}]},{"text":"OK? ","ticks":14010,"offset":51812.190992229655,"event_offsets":[{"offset":51812.190992229655,"char_count":0},{"offset":51812.190992229655,"char_count":4}]},{"text":"Take ","ticks":14010,"offset":51812.190992229655,"event_offsets":[{"offset":51812.190992229655,"char_count":0},{"offset":52707.162456906284,"char_count":5}]},{"text":"Take ","ticks":14252,"offset":52707.162456906284,"event_offsets":[{"offset":52707.162456906284,"char_count":5}]},{"text":"Take on on on me, ","ticks":14252,"offset":52707.162456906284,"event_offsets":[{"offset":52707.162456906284,"char_count":5},{"offset":54130.98069616456,"char_count":3},{"offset":54130.98069616456,"char_count":3},{"offset":54130.98069616456,"char_count":3},{"offset":55554.798935422834,"char_count":4}]},{"text":"me, ","ticks":15022,"offset":55554.798935422834,"event_offsets":[{"offset":55554.798935422834,"char_count":0},{"offset":55554.798935422834,"char_count":4}]},{"text":"me, ","ticks":15022,"offset":55554.798935422834,"event_offsets":[{"offset":55554.798935422834,"char_count":0},{"offset":55554.798935422834,"char_count":4}]},{"text":"(Take ","ticks":15022,"offset":55554.798935422834,"event_offsets":[{"offset":55554.798935422834,"char_count":0},{"offset":56978.61717468111,"char_count":6}]},{"text":"(Take ","ticks":15407,"offset":56978.61717468111,"event_offsets":[{"offset":56978.61717468111,"char_count":6}]},{"text":"(Take on on on me) ","ticks":15407,"offset":56978.61717468111,"event_offsets":[{"offset":56978.61717468111,"char_count":6},{"offset":57507.463949262754,"char_count":3},{"offset":57507.463949262754,"char_count":3},{"offset":57507.463949262754,"char_count":3},{"offset":57954.949681601065,"char_count":4}]},{"text":"me) ","ticks":15671,"offset":57954.949681601065,"event_offsets":[{"offset":57954.949681601065,"char_count":0},{"offset":57954.949681601065,"char_count":4}]},{"text":"me) ","ticks":15671,"offset":57954.949681601065,"event_offsets":[{"offset":57954.949681601065,"char_count":0},{"offset":57954.949681601065,"char_count":4}]},{"text":"Take ","ticks":15671,"offset":57954.949681601065,"event_offsets":[{"offset":57954.949681601065,"char_count":0},{"offset":58406.133643132256,"char_count":5}]},{"text":"Take ","ticks":15793,"offset":58406.133643132256,"event_offsets":[{"offset":58406.133643132256,"char_count":5}]},{"text":"Take me me me on ","ticks":15793,"offset":58406.133643132256,"event_offsets":[{"offset":58406.133643132256,"char_count":5},{"offset":59826.25365319765,"char_count":3},{"offset":59826.25365319765,"char_count":3},{"offset":59826.25365319765,"char_count":3},{"offset":61250.071892455926,"char_count":3}]},{"text":"on ","ticks":16562,"offset":61250.071892455926,"event_offsets":[{"offset":61250.071892455926,"char_count":0},{"offset":61250.071892455926,"char_count":3}]},{"text":"on ","ticks":16562,"offset":61250.071892455926,"event_offsets":[{"offset":61250.071892455926,"char_count":0},{"offset":61250.071892455926,"char_count":3}]},{"text":"(Take ","ticks":16562,"offset":61250.071892455926,"event_offsets":[{"offset":61250.071892455926,"char_count":0},{"offset":62677.58836090708,"char_count":6}]},{"text":"(Take ","ticks":16948,"offset":62677.58836090708,"event_offsets":[{"offset":62677.58836090708,"char_count":6}]},{"text":"(Take on on on me) ","ticks":16948,"offset":62677.58836090708,"event_offsets":[{"offset":62677.58836090708,"char_count":6},{"offset":63213.831593874485,"char_count":3},{"offset":63213.831593874485,"char_count":3},{"offset":63213.831593874485,"char_count":3},{"offset":63653.92086782704,"char_count":4}]},{"text":"me) ","ticks":17212,"offset":63653.92086782704,"event_offsets":[{"offset":63653.92086782704,"char_count":0},{"offset":63653.92086782704,"char_count":4}]},{"text":"me) ","ticks":17212,"offset":63653.92086782704,"event_offsets":[{"offset":63653.92086782704,"char_count":0},{"offset":63653.92086782704,"char_count":4}]},{"text":"I'll ","ticks":17212,"offset":63653.92086782704,"event_offsets":[{"offset":63653.92086782704,"char_count":0},{"offset":64101.406600165355,"char_count":5}]},{"text":"I'll ","ticks":17333,"offset":64101.406600165355,"event_offsets":[{"offset":64101.406600165355,"char_count":5}]},{"text":"I'll be be be gone ","ticks":17333,"offset":64101.406600165355,"event_offsets":[{"offset":64101.406600165355,"char_count":5},{"offset":65525.22483942363,"char_count":3},{"offset":65525.22483942363,"char_count":3},{"offset":65525.22483942363,"char_count":3},{"offset":66949.0430786819,"char_count":5}]},{"text":"gone ","ticks":18103,"offset":66949.0430786819,"event_offsets":[{"offset":66949.0430786819,"char_count":0},{"offset":66949.0430786819,"char_count":5}]},{"text":"gone ","ticks":18103,"offset":66949.0430786819,"event_offsets":[{"offset":66949.0430786819,"char_count":0},{"offset":66949.0430786819,"char_count":5}]},{"text":"In ","ticks":18103,"offset":66949.0430786819,"event_offsets":[{"offset":66949.0430786819,"char_count":0},{"offset":68727.89132045652,"char_count":3}]},{"text":"In ","ticks":18584,"offset":68727.89132045652,"event_offsets":[{"offset":68727.89132045652,"char_count":3}]},{"text":"In a a a day day day or or or two ","ticks":18584,"offset":68727.89132045652,"event_offsets":[{"offset":68727.89132045652,"char_count":3},{"offset":68909.10455090758,"char_count":2},{"offset":68909.10455090758,"char_count":2},{"offset":68909.10455090758,"char_count":2},{"offset":69267.83278261681,"char_count":4},{"offset":69267.83278261681,"char_count":4},{"offset":69267.83278261681,"char_count":4},{"offset":69441.6495546821,"char_count":3},{"offset":69441.6495546821,"char_count":3},{"offset":69441.6495546821,"char_count":3},{"offset":69804.07601558421,"char_count":4}]},{"text":"two ","ticks":18875,"offset":69804.07601558421,"event_offsets":[{"offset":69804.07601558421,"char_count":0},{"offset":69804.07601558421,"char_count":4}]},{"text":"","ticks":18875,"offset":69804.07601558421,"event_offsets":[{"offset":69804.07601558421,"char_count":0}]},{"text":"two ","ticks":18875,"offset":69804.07601558421,"event_offsets":[{"offset":69804.07601558421,"char_count":0},{"offset":69804.07601558421,"char_count":4}]},{"text":"","ticks":18875,"offset":69804.07601558421,"event_offsets":[{"offset":69804.07601558421,"char_count":0}]},{"text":"So ","ticks":18875,"offset":69804.07601558421,"event_offsets":[{"offset":69804.07601558421,"char_count":0},{"offset":75495.65074342443,"char_count":3}]},{"text":"So ","ticks":20414,"offset":75495.65074342443,"event_offsets":[{"offset":75495.65074342443,"char_count":3}]},{"text":"So needless needless needless to to to say ","ticks":20414,"offset":75495.65074342443,"event_offsets":[{"offset":75495.65074342443,"char_count":3},{"offset":76031.89397639183,"char_count":9},{"offset":76031.89397639183,"char_count":9},{"offset":76031.89397639183,"char_count":9},{"offset":76390.62220810105,"char_count":3},{"offset":76390.62220810105,"char_count":3},{"offset":76390.62220810105,"char_count":3},{"offset":76568.13720935922,"char_count":4}]},{"text":"say ","ticks":20704,"offset":76568.13720935922,"event_offsets":[{"offset":76568.13720935922,"char_count":0},{"offset":76568.13720935922,"char_count":4}]},{"text":"say ","ticks":20704,"offset":76568.13720935922,"event_offsets":[{"offset":76568.13720935922,"char_count":0},{"offset":76568.13720935922,"char_count":4}]},{"text":"I'm ","ticks":20704,"offset":76568.13720935922,"event_offsets":[{"offset":76568.13720935922,"char_count":0},{"offset":78346.98545113385,"char_count":4}]},{"text":"I'm ","ticks":21185,"offset":78346.98545113385,"event_offsets":[{"offset":78346.98545113385,"char_count":4}]},{"text":"I'm odds odds odds and and and ends ","ticks":21185,"offset":78346.98545113385,"event_offsets":[{"offset":78346.98545113385,"char_count":4},{"offset":78524.50045239202,"char_count":5},{"offset":78524.50045239202,"char_count":5},{"offset":78524.50045239202,"char_count":5},{"offset":78883.22868410125,"char_count":4},{"offset":78883.22868410125,"char_count":4},{"offset":78883.22868410125,"char_count":4},{"offset":79238.2586866176,"char_count":5}]},{"text":"ends ","ticks":21426,"offset":79238.2586866176,"event_offsets":[{"offset":79238.2586866176,"char_count":0},{"offset":79238.2586866176,"char_count":5}]},{"text":"ends ","ticks":21426,"offset":79238.2586866176,"event_offsets":[{"offset":79238.2586866176,"char_count":0},{"offset":79238.2586866176,"char_count":5}]},{"text":"But ","ticks":21426,"offset":79238.2586866176,"event_offsets":[{"offset":79238.2586866176,"char_count":0},{"offset":79952.01692084318,"char_count":4}]},{"text":"But ","ticks":21619,"offset":79952.01692084318,"event_offsets":[{"offset":79952.01692084318,"char_count":4}]},{"text":"But that's that's that's me me me that that that stumstumstumblblbling ing ing aaaway ","ticks":21619,"offset":79952.01692084318,"event_offsets":[{"offset":79952.01692084318,"char_count":4},{"offset":80307.04692335952,"char_count":7},{"offset":80307.04692335952,"char_count":7},{"offset":80307.04692335952,"char_count":7},{"offset":80484.5619246177,"char_count":3},{"offset":80484.5619246177,"char_count":3},{"offset":80484.5619246177,"char_count":3},{"offset":80839.59192713405,"char_count":5},{"offset":80839.59192713405,"char_count":5},{"offset":80839.59192713405,"char_count":5},{"offset":81194.6219296504,"char_count":4},{"offset":81194.6219296504,"char_count":4},{"offset":81194.6219296504,"char_count":4},{"offset":81730.8651626178,"char_count":2},{"offset":81730.8651626178,"char_count":2},{"offset":81730.8651626178,"char_count":2},{"offset":81908.38016387598,"char_count":4},{"offset":81908.38016387598,"char_count":4},{"offset":81908.38016387598,"char_count":4},{"offset":82089.59339432702,"char_count":1},{"offset":82089.59339432702,"char_count":1},{"offset":82089.59339432702,"char_count":1},{"offset":82444.62339684338,"char_count":4}]},{"text":"way ","ticks":22293,"offset":82444.62339684338,"event_offsets":[{"offset":82444.62339684338,"char_count":0},{"offset":82444.62339684338,"char_count":4}]},{"text":"way ","ticks":22293,"offset":82444.62339684338,"event_offsets":[{"offset":82444.62339684338,"char_count":0},{"offset":82444.62339684338,"char_count":4}]},{"text":"Slow","ticks":22293,"offset":82444.62339684338,"event_offsets":[{"offset":82444.62339684338,"char_count":0},{"offset":84045.95663735982,"char_count":4}]},{"text":"Slow","ticks":22726,"offset":84045.95663735982,"event_offsets":[{"offset":84045.95663735982,"char_count":4}]},{"text":"Slowly ly ly learlearlearning ning ning that that that life life life is is is OOOK. ","ticks":22726,"offset":84045.95663735982,"event_offsets":[{"offset":84045.95663735982,"char_count":4},{"offset":84223.471638618,"char_count":3},{"offset":84223.471638618,"char_count":3},{"offset":84223.471638618,"char_count":3},{"offset":84578.50164113435,"char_count":4},{"offset":84578.50164113435,"char_count":4},{"offset":84578.50164113435,"char_count":4},{"offset":84937.22987284357,"char_count":5},{"offset":84937.22987284357,"char_count":5},{"offset":84937.22987284357,"char_count":5},{"offset":85292.25987535993,"char_count":5},{"offset":85292.25987535993,"char_count":5},{"offset":85292.25987535993,"char_count":5},{"offset":85647.28987787628,"char_count":5},{"offset":85647.28987787628,"char_count":5},{"offset":85647.28987787628,"char_count":5},{"offset":86006.01810958551,"char_count":3},{"offset":86006.01810958551,"char_count":3},{"offset":86006.01810958551,"char_count":3},{"offset":86183.53311084368,"char_count":1},{"offset":86183.53311084368,"char_count":1},{"offset":86183.53311084368,"char_count":1},{"offset":86538.56311336003,"char_count":3}]},{"text":"K. ","ticks":23400,"offset":86538.56311336003,"event_offsets":[{"offset":86538.56311336003,"char_count":0},{"offset":86538.56311336003,"char_count":3}]},{"text":"K. ","ticks":23400,"offset":86538.56311336003,"event_offsets":[{"offset":86538.56311336003,"char_count":0},{"offset":86538.56311336003,"char_count":3}]},{"text":"Say ","ticks":23400,"offset":86538.56311336003,"event_offsets":[{"offset":86538.56311336003,"char_count":0},{"offset":87248.62311839272,"char_count":4}]},{"text":"Say ","ticks":23592,"offset":87248.62311839272,"event_offsets":[{"offset":87248.62311839272,"char_count":4}]},{"text":"Say afafafter ter ter me ","ticks":23592,"offset":87248.62311839272,"event_offsets":[{"offset":87248.62311839272,"char_count":4},{"offset":87788.56458055301,"char_count":2},{"offset":87788.56458055301,"char_count":2},{"offset":87788.56458055301,"char_count":2},{"offset":87962.3813526183,"char_count":4},{"offset":87962.3813526183,"char_count":4},{"offset":87962.3813526183,"char_count":4},{"offset":88139.89635387647,"char_count":3}]},{"text":"me ","ticks":23833,"offset":88139.89635387647,"event_offsets":[{"offset":88139.89635387647,"char_count":0},{"offset":88139.89635387647,"char_count":3}]},{"text":"me ","ticks":23833,"offset":88139.89635387647,"event_offsets":[{"offset":88139.89635387647,"char_count":0},{"offset":88139.89635387647,"char_count":3}]},{"text":"It's ","ticks":23833,"offset":88139.89635387647,"event_offsets":[{"offset":88139.89635387647,"char_count":0},{"offset":90099.95782610215,"char_count":5}]},{"text":"It's ","ticks":24363,"offset":90099.95782610215,"event_offsets":[{"offset":90099.95782610215,"char_count":5}]},{"text":"It's no no no betbetbetter ter ter to to to be be be safe safe safe than than than sorry ","ticks":24363,"offset":90099.95782610215,"event_offsets":[{"offset":90099.95782610215,"char_count":5},{"offset":90277.47282736033,"char_count":3},{"offset":90277.47282736033,"char_count":3},{"offset":90277.47282736033,"char_count":3},{"offset":90454.9878286185,"char_count":3},{"offset":90454.9878286185,"char_count":3},{"offset":90454.9878286185,"char_count":3},{"offset":90636.20105906954,"char_count":4},{"offset":90636.20105906954,"char_count":4},{"offset":90636.20105906954,"char_count":4},{"offset":90810.01783113484,"char_count":3},{"offset":90810.01783113484,"char_count":3},{"offset":90810.01783113484,"char_count":3},{"offset":90991.2310615859,"char_count":3},{"offset":90991.2310615859,"char_count":3},{"offset":90991.2310615859,"char_count":3},{"offset":91165.04783365119,"char_count":5},{"offset":91165.04783365119,"char_count":5},{"offset":91165.04783365119,"char_count":5},{"offset":91346.26106410225,"char_count":5},{"offset":91346.26106410225,"char_count":5},{"offset":91346.26106410225,"char_count":5},{"offset":91701.29106661859,"char_count":6}]},{"text":"sorry ","ticks":24796,"offset":91701.29106661859,"event_offsets":[{"offset":91701.29106661859,"char_count":0},{"offset":91701.29106661859,"char_count":6}]},{"text":"sorry ","ticks":24796,"offset":91701.29106661859,"event_offsets":[{"offset":91701.29106661859,"char_count":0},{"offset":91701.29106661859,"char_count":6}]},{"text":"Take ","ticks":24796,"offset":91701.29106661859,"event_offsets":[{"offset":91701.29106661859,"char_count":0},{"offset":92592.56430210234,"char_count":5}]},{"text":"Take ","ticks":25037,"offset":92592.56430210234,"event_offsets":[{"offset":92592.56430210234,"char_count":5}]},{"text":"Take on on on me, ","ticks":25037,"offset":92592.56430210234,"event_offsets":[{"offset":92592.56430210234,"char_count":5},{"offset":94016.38254136062,"char_count":3},{"offset":94016.38254136062,"char_count":3},{"offset":94016.38254136062,"char_count":3},{"offset":95440.20078061889,"char_count":4}]},{"text":"me, ","ticks":25807,"offset":95440.20078061889,"event_offsets":[{"offset":95440.20078061889,"char_count":0},{"offset":95440.20078061889,"char_count":4}]},{"text":"me, ","ticks":25807,"offset":95440.20078061889,"event_offsets":[{"offset":95440.20078061889,"char_count":0},{"offset":95440.20078061889,"char_count":4}]},{"text":"(Take ","ticks":25807,"offset":95440.20078061889,"event_offsets":[{"offset":95440.20078061889,"char_count":0},{"offset":96864.01901987717,"char_count":6}]},{"text":"(Take ","ticks":26192,"offset":96864.01901987717,"event_offsets":[{"offset":96864.01901987717,"char_count":6}]},{"text":"(Take on on on me) ","ticks":26192,"offset":96864.01901987717,"event_offsets":[{"offset":96864.01901987717,"char_count":6},{"offset":97400.26225284456,"char_count":3},{"offset":97400.26225284456,"char_count":3},{"offset":97400.26225284456,"char_count":3},{"offset":97840.35152679712,"char_count":4}]},{"text":"me) ","ticks":26456,"offset":97840.35152679712,"event_offsets":[{"offset":97840.35152679712,"char_count":0},{"offset":97840.35152679712,"char_count":4}]},{"text":"me) ","ticks":26456,"offset":97840.35152679712,"event_offsets":[{"offset":97840.35152679712,"char_count":0},{"offset":97840.35152679712,"char_count":4}]},{"text":"Take ","ticks":26456,"offset":97840.35152679712,"event_offsets":[{"offset":97840.35152679712,"char_count":0},{"offset":98291.53548832831,"char_count":5}]},{"text":"Take ","ticks":26578,"offset":98291.53548832831,"event_offsets":[{"offset":98291.53548832831,"char_count":5}]},{"text":"Take me me me on ","ticks":26578,"offset":98291.53548832831,"event_offsets":[{"offset":98291.53548832831,"char_count":5},{"offset":99715.3537275866,"char_count":3},{"offset":99715.3537275866,"char_count":3},{"offset":99715.3537275866,"char_count":3},{"offset":101135.47373765199,"char_count":3}]},{"text":"on ","ticks":27347,"offset":101135.47373765199,"event_offsets":[{"offset":101135.47373765199,"char_count":0},{"offset":101135.47373765199,"char_count":3}]},{"text":"on ","ticks":27347,"offset":101135.47373765199,"event_offsets":[{"offset":101135.47373765199,"char_count":0},{"offset":101135.47373765199,"char_count":3}]},{"text":"(Take ","ticks":27347,"offset":101135.47373765199,"event_offsets":[{"offset":101135.47373765199,"char_count":0},{"offset":102562.99020610315,"char_count":6}]},{"text":"(Take ","ticks":27733,"offset":102562.99020610315,"event_offsets":[{"offset":102562.99020610315,"char_count":6}]},{"text":"(Take on on on me) ","ticks":27733,"offset":102562.99020610315,"event_offsets":[{"offset":102562.99020610315,"char_count":6},{"offset":103099.23343907055,"char_count":3},{"offset":103099.23343907055,"char_count":3},{"offset":103099.23343907055,"char_count":3},{"offset":103539.3227130231,"char_count":4}]},{"text":"me) ","ticks":27997,"offset":103539.3227130231,"event_offsets":[{"offset":103539.3227130231,"char_count":0},{"offset":103539.3227130231,"char_count":4}]},{"text":"me) ","ticks":27997,"offset":103539.3227130231,"event_offsets":[{"offset":103539.3227130231,"char_count":0},{"offset":103539.3227130231,"char_count":4}]},{"text":"I'll ","ticks":27997,"offset":103539.3227130231,"event_offsets":[{"offset":103539.3227130231,"char_count":0},{"offset":103986.80844536141,"char_count":5}]},{"text":"I'll ","ticks":28118,"offset":103986.80844536141,"event_offsets":[{"offset":103986.80844536141,"char_count":5}]},{"text":"I'll be be be gone ","ticks":28118,"offset":103986.80844536141,"event_offsets":[{"offset":103986.80844536141,"char_count":5},{"offset":105410.6266846197,"char_count":3},{"offset":105410.6266846197,"char_count":3},{"offset":105410.6266846197,"char_count":3},{"offset":106834.44492387796,"char_count":5}]},{"text":"gone ","ticks":28888,"offset":106834.44492387796,"event_offsets":[{"offset":106834.44492387796,"char_count":0},{"offset":106834.44492387796,"char_count":5}]},{"text":"gone ","ticks":28888,"offset":106834.44492387796,"event_offsets":[{"offset":106834.44492387796,"char_count":0},{"offset":106834.44492387796,"char_count":5}]},{"text":"In ","ticks":28888,"offset":106834.44492387796,"event_offsets":[{"offset":106834.44492387796,"char_count":0},{"offset":108613.29316565259,"char_count":3}]},{"text":"In ","ticks":29369,"offset":108613.29316565259,"event_offsets":[{"offset":108613.29316565259,"char_count":3}]},{"text":"In a a a day day day or or or two ","ticks":29369,"offset":108613.29316565259,"event_offsets":[{"offset":108613.29316565259,"char_count":3},{"offset":108794.50639610364,"char_count":2},{"offset":108794.50639610364,"char_count":2},{"offset":108794.50639610364,"char_count":2},{"offset":109153.23462781287,"char_count":4},{"offset":109153.23462781287,"char_count":4},{"offset":109153.23462781287,"char_count":4},{"offset":109327.05139987817,"char_count":3},{"offset":109327.05139987817,"char_count":3},{"offset":109327.05139987817,"char_count":3},{"offset":109689.47786078027,"char_count":4}]},{"text":"two ","ticks":29660,"offset":109689.47786078027,"event_offsets":[{"offset":109689.47786078027,"char_count":0},{"offset":109689.47786078027,"char_count":4}]},{"text":"","ticks":29660,"offset":109689.47786078027,"event_offsets":[{"offset":109689.47786078027,"char_count":0}]},{"text":"two ","ticks":29660,"offset":109689.47786078027,"event_offsets":[{"offset":109689.47786078027,"char_count":0},{"offset":109689.47786078027,"char_count":4}]},{"text":"","ticks":29660,"offset":109689.47786078027,"event_offsets":[{"offset":109689.47786078027,"char_count":0}]},{"text":"Oh ","ticks":29660,"offset":109689.47786078027,"event_offsets":[{"offset":109689.47786078027,"char_count":0},{"offset":155255.35974623793,"char_count":3}]},{"text":"Oh ","ticks":41981,"offset":155255.35974623793,"event_offsets":[{"offset":155255.35974623793,"char_count":3}]},{"text":"Oh the the the things things things you you you say ","ticks":41981,"offset":155255.35974623793,"event_offsets":[{"offset":155255.35974623793,"char_count":3},{"offset":155610.38974875427,"char_count":4},{"offset":155610.38974875427,"char_count":4},{"offset":155610.38974875427,"char_count":4},{"offset":155802.69766678396,"char_count":7},{"offset":155802.69766678396,"char_count":7},{"offset":155802.69766678396,"char_count":7},{"offset":156161.42589849318,"char_count":4},{"offset":156161.42589849318,"char_count":4},{"offset":156161.42589849318,"char_count":4},{"offset":156338.94089975135,"char_count":4}]},{"text":"say ","ticks":42274,"offset":156338.94089975135,"event_offsets":[{"offset":156338.94089975135,"char_count":0},{"offset":156338.94089975135,"char_count":4}]},{"text":"say ","ticks":42274,"offset":156338.94089975135,"event_offsets":[{"offset":156338.94089975135,"char_count":0},{"offset":156338.94089975135,"char_count":4}]},{"text":"Is ","ticks":42274,"offset":156338.94089975135,"event_offsets":[{"offset":156338.94089975135,"char_count":0},{"offset":158117.78914152598,"char_count":3}]},{"text":"Is ","ticks":42755,"offset":158117.78914152598,"event_offsets":[{"offset":158117.78914152598,"char_count":3}]},{"text":"Is it it it live live live or ","ticks":42755,"offset":158117.78914152598,"event_offsets":[{"offset":158117.78914152598,"char_count":3},{"offset":158295.30414278415,"char_count":3},{"offset":158295.30414278415,"char_count":3},{"offset":158295.30414278415,"char_count":3},{"offset":158654.03237449337,"char_count":5},{"offset":158654.03237449337,"char_count":5},{"offset":158654.03237449337,"char_count":5},{"offset":159009.06237700972,"char_count":3}]},{"text":"or ","ticks":42996,"offset":159009.06237700972,"event_offsets":[{"offset":159009.06237700972,"char_count":0},{"offset":159009.06237700972,"char_count":3}]},{"text":"or ","ticks":42996,"offset":159009.06237700972,"event_offsets":[{"offset":159009.06237700972,"char_count":0},{"offset":159009.06237700972,"char_count":3}]},{"text":"Just ","ticks":42996,"offset":159009.06237700972,"event_offsets":[{"offset":159009.06237700972,"char_count":0},{"offset":159722.8206112353,"char_count":5}]},{"text":"Just ","ticks":43189,"offset":159722.8206112353,"event_offsets":[{"offset":159722.8206112353,"char_count":5}]},{"text":"Just to to to play play play my my my worworworries ries ries aaawawaway ","ticks":43189,"offset":159722.8206112353,"event_offsets":[{"offset":159722.8206112353,"char_count":5},{"offset":160077.85061375165,"char_count":3},{"offset":160077.85061375165,"char_count":3},{"offset":160077.85061375165,"char_count":3},{"offset":160255.36561500982,"char_count":5},{"offset":160255.36561500982,"char_count":5},{"offset":160255.36561500982,"char_count":5},{"offset":160610.39561752617,"char_count":3},{"offset":160610.39561752617,"char_count":3},{"offset":160610.39561752617,"char_count":3},{"offset":160965.42562004252,"char_count":3},{"offset":160965.42562004252,"char_count":3},{"offset":160965.42562004252,"char_count":3},{"offset":161501.66885300993,"char_count":5},{"offset":161501.66885300993,"char_count":5},{"offset":161501.66885300993,"char_count":5},{"offset":161679.1838542681,"char_count":1},{"offset":161679.1838542681,"char_count":1},{"offset":161679.1838542681,"char_count":1},{"offset":161860.39708471915,"char_count":2},{"offset":161860.39708471915,"char_count":2},{"offset":161860.39708471915,"char_count":2},{"offset":162215.4270872355,"char_count":2}]},{"text":"y ","ticks":43863,"offset":162215.4270872355,"event_offsets":[{"offset":162215.4270872355,"char_count":0},{"offset":162215.4270872355,"char_count":2}]},{"text":"y ","ticks":43863,"offset":162215.4270872355,"event_offsets":[{"offset":162215.4270872355,"char_count":0},{"offset":162215.4270872355,"char_count":2}]},{"text":"You're ","ticks":43863,"offset":162215.4270872355,"event_offsets":[{"offset":162215.4270872355,"char_count":0},{"offset":163816.76032775195,"char_count":7}]},{"text":"You're ","ticks":44296,"offset":163816.76032775195,"event_offsets":[{"offset":163816.76032775195,"char_count":7}]},{"text":"You're all all all the the the things things things I've I've I've got got got to to to rereremember ","ticks":44296,"offset":163816.76032775195,"event_offsets":[{"offset":163816.76032775195,"char_count":7},{"offset":163994.27532901012,"char_count":4},{"offset":163994.27532901012,"char_count":4},{"offset":163994.27532901012,"char_count":4},{"offset":164349.30533152647,"char_count":4},{"offset":164349.30533152647,"char_count":4},{"offset":164349.30533152647,"char_count":4},{"offset":164708.0335632357,"char_count":7},{"offset":164708.0335632357,"char_count":7},{"offset":164708.0335632357,"char_count":7},{"offset":165063.06356575206,"char_count":5},{"offset":165063.06356575206,"char_count":5},{"offset":165063.06356575206,"char_count":5},{"offset":165418.0935682684,"char_count":4},{"offset":165418.0935682684,"char_count":4},{"offset":165418.0935682684,"char_count":4},{"offset":165776.82179997762,"char_count":3},{"offset":165776.82179997762,"char_count":3},{"offset":165776.82179997762,"char_count":3},{"offset":165954.3368012358,"char_count":2},{"offset":165954.3368012358,"char_count":2},{"offset":165954.3368012358,"char_count":2},{"offset":166309.36680375214,"char_count":7}]},{"text":"member ","ticks":44970,"offset":166309.36680375214,"event_offsets":[{"offset":166309.36680375214,"char_count":0},{"offset":166309.36680375214,"char_count":7}]},{"text":"member ","ticks":44970,"offset":166309.36680375214,"event_offsets":[{"offset":166309.36680375214,"char_count":0},{"offset":166309.36680375214,"char_count":7}]},{"text":"Shy","ticks":44970,"offset":166309.36680375214,"event_offsets":[{"offset":166309.36680375214,"char_count":0},{"offset":167019.42680878483,"char_count":3}]},{"text":"Shy","ticks":45162,"offset":167019.42680878483,"event_offsets":[{"offset":167019.42680878483,"char_count":3}]},{"text":"Shying ing ing aaaway ","ticks":45162,"offset":167019.42680878483,"event_offsets":[{"offset":167019.42680878483,"char_count":3},{"offset":167555.67004175225,"char_count":4},{"offset":167555.67004175225,"char_count":4},{"offset":167555.67004175225,"char_count":4},{"offset":167733.18504301042,"char_count":1},{"offset":167733.18504301042,"char_count":1},{"offset":167733.18504301042,"char_count":1},{"offset":167910.7000442686,"char_count":4}]},{"text":"way ","ticks":45403,"offset":167910.7000442686,"event_offsets":[{"offset":167910.7000442686,"char_count":0},{"offset":167910.7000442686,"char_count":4}]},{"text":"way ","ticks":45403,"offset":167910.7000442686,"event_offsets":[{"offset":167910.7000442686,"char_count":0},{"offset":167910.7000442686,"char_count":4}]},{"text":"I'll ","ticks":45403,"offset":167910.7000442686,"event_offsets":[{"offset":167910.7000442686,"char_count":0},{"offset":169870.76151649427,"char_count":5}]},{"text":"I'll ","ticks":45933,"offset":169870.76151649427,"event_offsets":[{"offset":169870.76151649427,"char_count":5}]},{"text":"I'll be be be cococoming ming ming for for for you you you aaanynynyway ","ticks":45933,"offset":169870.76151649427,"event_offsets":[{"offset":169870.76151649427,"char_count":5},{"offset":170048.27651775244,"char_count":3},{"offset":170048.27651775244,"char_count":3},{"offset":170048.27651775244,"char_count":3},{"offset":170225.7915190106,"char_count":2},{"offset":170225.7915190106,"char_count":2},{"offset":170225.7915190106,"char_count":2},{"offset":170407.0047494617,"char_count":5},{"offset":170407.0047494617,"char_count":5},{"offset":170407.0047494617,"char_count":5},{"offset":170580.82152152696,"char_count":4},{"offset":170580.82152152696,"char_count":4},{"offset":170580.82152152696,"char_count":4},{"offset":170762.03475197803,"char_count":4},{"offset":170762.03475197803,"char_count":4},{"offset":170762.03475197803,"char_count":4},{"offset":170939.5497532362,"char_count":1},{"offset":170939.5497532362,"char_count":1},{"offset":170939.5497532362,"char_count":1},{"offset":171117.06475449438,"char_count":2},{"offset":171117.06475449438,"char_count":2},{"offset":171117.06475449438,"char_count":2},{"offset":171472.09475701072,"char_count":4}]},{"text":"way ","ticks":46366,"offset":171472.09475701072,"event_offsets":[{"offset":171472.09475701072,"char_count":0},{"offset":171472.09475701072,"char_count":4}]},{"text":"way ","ticks":46366,"offset":171472.09475701072,"event_offsets":[{"offset":171472.09475701072,"char_count":0},{"offset":171472.09475701072,"char_count":4}]},{"text":"Take ","ticks":46366,"offset":171472.09475701072,"event_offsets":[{"offset":171472.09475701072,"char_count":0},{"offset":172363.36799249446,"char_count":5}]},{"text":"Take ","ticks":46607,"offset":172363.36799249446,"event_offsets":[{"offset":172363.36799249446,"char_count":5}]},{"text":"Take on on on me, ","ticks":46607,"offset":172363.36799249446,"event_offsets":[{"offset":172363.36799249446,"char_count":5},{"offset":173790.8844609456,"char_count":3},{"offset":173790.8844609456,"char_count":3},{"offset":173790.8844609456,"char_count":3},{"offset":175214.7027002039,"char_count":4}]},{"text":"me, ","ticks":47378,"offset":175214.7027002039,"event_offsets":[{"offset":175214.7027002039,"char_count":0},{"offset":175214.7027002039,"char_count":4}]},{"text":"me, ","ticks":47378,"offset":175214.7027002039,"event_offsets":[{"offset":175214.7027002039,"char_count":0},{"offset":175214.7027002039,"char_count":4}]},{"text":"(Take ","ticks":47378,"offset":175214.7027002039,"event_offsets":[{"offset":175214.7027002039,"char_count":0},{"offset":176638.52093946218,"char_count":6}]},{"text":"(Take ","ticks":47763,"offset":176638.52093946218,"event_offsets":[{"offset":176638.52093946218,"char_count":6}]},{"text":"(Take on on on me) ","ticks":47763,"offset":176638.52093946218,"event_offsets":[{"offset":176638.52093946218,"char_count":6},{"offset":177171.0659432367,"char_count":3},{"offset":177171.0659432367,"char_count":3},{"offset":177171.0659432367,"char_count":3},{"offset":177614.85344638213,"char_count":4}]},{"text":"me) ","ticks":48027,"offset":177614.85344638213,"event_offsets":[{"offset":177614.85344638213,"char_count":0},{"offset":177614.85344638213,"char_count":4}]},{"text":"me) ","ticks":48027,"offset":177614.85344638213,"event_offsets":[{"offset":177614.85344638213,"char_count":0},{"offset":177614.85344638213,"char_count":4}]},{"text":"Take ","ticks":48027,"offset":177614.85344638213,"event_offsets":[{"offset":177614.85344638213,"char_count":0},{"offset":178066.03740791333,"char_count":5}]},{"text":"Take ","ticks":48149,"offset":178066.03740791333,"event_offsets":[{"offset":178066.03740791333,"char_count":5}]},{"text":"Take me me me on ","ticks":48149,"offset":178066.03740791333,"event_offsets":[{"offset":178066.03740791333,"char_count":5},{"offset":179489.8556471716,"char_count":3},{"offset":179489.8556471716,"char_count":3},{"offset":179489.8556471716,"char_count":3},{"offset":180913.67388642987,"char_count":3}]},{"text":"on ","ticks":48919,"offset":180913.67388642987,"event_offsets":[{"offset":180913.67388642987,"char_count":0},{"offset":180913.67388642987,"char_count":3}]},{"text":"on ","ticks":48919,"offset":180913.67388642987,"event_offsets":[{"offset":180913.67388642987,"char_count":0},{"offset":180913.67388642987,"char_count":3}]},{"text":"(Take ","ticks":48919,"offset":180913.67388642987,"event_offsets":[{"offset":180913.67388642987,"char_count":0},{"offset":182337.49212568815,"char_count":6}]},{"text":"(Take ","ticks":49304,"offset":182337.49212568815,"event_offsets":[{"offset":182337.49212568815,"char_count":6}]},{"text":"(Take on on on me) ","ticks":49304,"offset":182337.49212568815,"event_offsets":[{"offset":182337.49212568815,"char_count":6},{"offset":182866.3389002698,"char_count":3},{"offset":182866.3389002698,"char_count":3},{"offset":182866.3389002698,"char_count":3},{"offset":183317.52286180097,"char_count":4}]},{"text":"me) ","ticks":49569,"offset":183317.52286180097,"event_offsets":[{"offset":183317.52286180097,"char_count":0},{"offset":183317.52286180097,"char_count":4}]},{"text":"me) ","ticks":49569,"offset":183317.52286180097,"event_offsets":[{"offset":183317.52286180097,"char_count":0},{"offset":183317.52286180097,"char_count":4}]},{"text":"I'll ","ticks":49569,"offset":183317.52286180097,"event_offsets":[{"offset":183317.52286180097,"char_count":0},{"offset":183765.0085941393,"char_count":5}]},{"text":"I'll ","ticks":49690,"offset":183765.0085941393,"event_offsets":[{"offset":183765.0085941393,"char_count":5}]},{"text":"I'll be be be gone ","ticks":49690,"offset":183765.0085941393,"event_offsets":[{"offset":183765.0085941393,"char_count":5},{"offset":185185.12860420468,"char_count":3},{"offset":185185.12860420468,"char_count":3},{"offset":185185.12860420468,"char_count":3},{"offset":186612.64507265584,"char_count":5}]},{"text":"gone ","ticks":50460,"offset":186612.64507265584,"event_offsets":[{"offset":186612.64507265584,"char_count":0},{"offset":186612.64507265584,"char_count":5}]},{"text":"gone ","ticks":50460,"offset":186612.64507265584,"event_offsets":[{"offset":186612.64507265584,"char_count":0},{"offset":186612.64507265584,"char_count":5}]},{"text":"In ","ticks":50460,"offset":186612.64507265584,"event_offsets":[{"offset":186612.64507265584,"char_count":0},{"offset":188391.49331443047,"char_count":3}]},{"text":"In ","ticks":50941,"offset":188391.49331443047,"event_offsets":[{"offset":188391.49331443047,"char_count":3}]},{"text":"In a a a day day day or.two ","ticks":50941,"offset":188391.49331443047,"event_offsets":[{"offset":188391.49331443047,"char_count":3},{"offset":188565.31008649577,"char_count":2},{"offset":188565.31008649577,"char_count":2},{"offset":188565.31008649577,"char_count":2},{"offset":188924.03831820498,"char_count":4},{"offset":188924.03831820498,"char_count":4},{"offset":188924.03831820498,"char_count":4},{"offset":189105.25154865606,"char_count":7}]},{"text":"or.two ","ticks":51134,"offset":189105.25154865606,"event_offsets":[{"offset":189105.25154865606,"char_count":0},{"offset":189105.25154865606,"char_count":7}]},{"text":"or.two ","ticks":51134,"offset":189105.25154865606,"event_offsets":[{"offset":189105.25154865606,"char_count":0},{"offset":189105.25154865606,"char_count":7}]},{"text":"Take ","ticks":51134,"offset":189105.25154865606,"event_offsets":[{"offset":189105.25154865606,"char_count":0},{"offset":189463.97978036528,"char_count":5}]},{"text":"Take ","ticks":51231,"offset":189463.97978036528,"event_offsets":[{"offset":189463.97978036528,"char_count":5}]},{"text":"Take on on on me, ","ticks":51231,"offset":189463.97978036528,"event_offsets":[{"offset":189463.97978036528,"char_count":5},{"offset":190884.09979043066,"char_count":3},{"offset":190884.09979043066,"char_count":3},{"offset":190884.09979043066,"char_count":3},{"offset":192307.91802968894,"char_count":4}]},{"text":"me, ","ticks":52000,"offset":192307.91802968894,"event_offsets":[{"offset":192307.91802968894,"char_count":0},{"offset":192307.91802968894,"char_count":4}]},{"text":"me, ","ticks":52000,"offset":192307.91802968894,"event_offsets":[{"offset":192307.91802968894,"char_count":0},{"offset":192307.91802968894,"char_count":4}]},{"text":"(Take ","ticks":52000,"offset":192307.91802968894,"event_offsets":[{"offset":192307.91802968894,"char_count":0},{"offset":193731.73626894722,"char_count":6}]},{"text":"(Take ","ticks":52385,"offset":193731.73626894722,"event_offsets":[{"offset":193731.73626894722,"char_count":6}]},{"text":"(Take on on on me) ","ticks":52385,"offset":193731.73626894722,"event_offsets":[{"offset":193731.73626894722,"char_count":6},{"offset":194264.28127272174,"char_count":3},{"offset":194264.28127272174,"char_count":3},{"offset":194264.28127272174,"char_count":3},{"offset":194804.22273488203,"char_count":4}]},{"text":"me) ","ticks":52675,"offset":194804.22273488203,"event_offsets":[{"offset":194804.22273488203,"char_count":0},{"offset":194804.22273488203,"char_count":4}]},{"text":"me) ","ticks":52675,"offset":194804.22273488203,"event_offsets":[{"offset":194804.22273488203,"char_count":0},{"offset":194804.22273488203,"char_count":4}]},{"text":"Take ","ticks":52675,"offset":194804.22273488203,"event_offsets":[{"offset":194804.22273488203,"char_count":0},{"offset":195159.25273739838,"char_count":5}]},{"text":"Take ","ticks":52771,"offset":195159.25273739838,"event_offsets":[{"offset":195159.25273739838,"char_count":5}]},{"text":"Take me me me on ","ticks":52771,"offset":195159.25273739838,"event_offsets":[{"offset":195159.25273739838,"char_count":5},{"offset":196583.07097665663,"char_count":3},{"offset":196583.07097665663,"char_count":3},{"offset":196583.07097665663,"char_count":3},{"offset":198006.8892159149,"char_count":3}]},{"text":"on ","ticks":53541,"offset":198006.8892159149,"event_offsets":[{"offset":198006.8892159149,"char_count":0},{"offset":198006.8892159149,"char_count":3}]},{"text":"on ","ticks":53541,"offset":198006.8892159149,"event_offsets":[{"offset":198006.8892159149,"char_count":0},{"offset":198006.8892159149,"char_count":3}]},{"text":"(Take ","ticks":53541,"offset":198006.8892159149,"event_offsets":[{"offset":198006.8892159149,"char_count":0},{"offset":199434.40568436607,"char_count":6}]},{"text":"(Take ","ticks":53927,"offset":199434.40568436607,"event_offsets":[{"offset":199434.40568436607,"char_count":6}]},{"text":"(Take on on on me) ","ticks":53927,"offset":199434.40568436607,"event_offsets":[{"offset":199434.40568436607,"char_count":6},{"offset":199963.2524589477,"char_count":3},{"offset":199963.2524589477,"char_count":3},{"offset":199963.2524589477,"char_count":3},{"offset":200410.73819128601,"char_count":4}]},{"text":"me) ","ticks":54191,"offset":200410.73819128601,"event_offsets":[{"offset":200410.73819128601,"char_count":0},{"offset":200410.73819128601,"char_count":4}]},{"text":"me) ","ticks":54191,"offset":200410.73819128601,"event_offsets":[{"offset":200410.73819128601,"char_count":0},{"offset":200410.73819128601,"char_count":4}]},{"text":"I'll ","ticks":54191,"offset":200410.73819128601,"event_offsets":[{"offset":200410.73819128601,"char_count":0},{"offset":200858.22392362435,"char_count":5}]},{"text":"I'll ","ticks":54312,"offset":200858.22392362435,"event_offsets":[{"offset":200858.22392362435,"char_count":5}]},{"text":"I'll be be be gone ","ticks":54312,"offset":200858.22392362435,"event_offsets":[{"offset":200858.22392362435,"char_count":5},{"offset":202282.04216288263,"char_count":3},{"offset":202282.04216288263,"char_count":3},{"offset":202282.04216288263,"char_count":3},{"offset":203705.86040214088,"char_count":5}]},{"text":"gone ","ticks":55082,"offset":203705.86040214088,"event_offsets":[{"offset":203705.86040214088,"char_count":0},{"offset":203705.86040214088,"char_count":5}]},{"text":"gone ","ticks":55082,"offset":203705.86040214088,"event_offsets":[{"offset":203705.86040214088,"char_count":0},{"offset":203705.86040214088,"char_count":5}]},{"text":"In ","ticks":55082,"offset":203705.86040214088,"event_offsets":[{"offset":203705.86040214088,"char_count":0},{"offset":205484.7086439155,"char_count":3}]},{"text":"In ","ticks":55563,"offset":205484.7086439155,"event_offsets":[{"offset":205484.7086439155,"char_count":3}]},{"text":"In a a a day day day or or or two ","ticks":55563,"offset":205484.7086439155,"event_offsets":[{"offset":205484.7086439155,"char_count":3},{"offset":205658.5254159808,"char_count":2},{"offset":205658.5254159808,"char_count":2},{"offset":205658.5254159808,"char_count":2},{"offset":206017.25364769003,"char_count":4},{"offset":206017.25364769003,"char_count":4},{"offset":206017.25364769003,"char_count":4},{"offset":206198.4668781411,"char_count":3},{"offset":206198.4668781411,"char_count":3},{"offset":206198.4668781411,"char_count":3},{"offset":206557.19510985032,"char_count":4}]},{"text":"","ticks":55853,"offset":206557.19510985032,"event_offsets":[{"offset":206557.19510985032,"char_count":0}]},{"text":"two ","ticks":55853,"offset":206557.19510985032,"event_offsets":[{"offset":206557.19510985032,"char_count":0},{"offset":206557.19510985032,"char_count":4}]},{"text":"","ticks":55853,"offset":206557.19510985032,"event_offsets":[{"offset":206557.19510985032,"char_count":0}]},{"text":"two ","ticks":55853,"offset":206557.19510985032,"event_offsets":[{"offset":206557.19510985032,"char_count":0},{"offset":206557.19510985032,"char_count":4}]},{"text":"","ticks":55853,"offset":206557.19510985032,"event_offsets":[{"offset":206557.19510985032,"char_count":0}]},{"text":"","ticks":55853,"offset":206557.19510985032,"event_offsets":[{"offset":206557.19510985032,"char_count":0}]}]