[{"text":"When I think back on these times ","ticks":16780,"offset":16259.68030608403,"event_offsets":[{"offset":16259.68030608403,"char_count":5},{"offset":16511.618141577586,"char_count":2},{"offset":16763.55597707114,"char_count":6},{"offset":17193.788280760135,"char_count":5},{"offset":17686.03605164754,"char_count":3},{"offset":17926.345987041394,"char_count":6},{"offset":18174.40785583505,"char_count":6}]},{"text":"","ticks":18756,"offset":18174.40785583505,"event_offsets":[{"offset":18174.40785583505,"char_count":0}]},{"text":"and the dreams we left behind ","ticks":18756,"offset":18174.40785583505,"event_offsets":[{"offset":18174.40785583505,"char_count":0},{"offset":19957.352537789433,"char_count":4},{"offset":20209.290373282987,"char_count":4},{"offset":20457.352242076642,"char_count":7},{"offset":20957.35194636385,"char_count":3},{"offset":21426.343917051854,"char_count":5},{"offset":21887.583954340054,"char_count":2},{"offset":22135.645823133706,"char_count":5}]},{"text":"","ticks":22844,"offset":22135.645823133706,"event_offsets":[{"offset":22135.645823133706,"char_count":0}]},{"text":"are we glad 'cause I was blessed to get ","ticks":22844,"offset":22135.645823133706,"event_offsets":[{"offset":22135.645823133706,"char_count":0},{"offset":23686.032503094044,"char_count":4},{"offset":23922.466471787997,"char_count":3},{"offset":24158.900440481946,"char_count":5},{"offset":24635.64434456975,"char_count":7},{"offset":24864.3263798639,"char_count":2},{"offset":25558.124419146152,"char_count":4},{"offset":25825.566121439308,"char_count":8},{"offset":26503.860293921956,"char_count":3},{"offset":26775.177962915015,"char_count":4}]},{"text":"","ticks":27632,"offset":26775.177962915015,"event_offsets":[{"offset":26775.177962915015,"char_count":0}]},{"text":"to have you in my life ","ticks":27632,"offset":26775.177962915015,"event_offsets":[{"offset":26775.177962915015,"char_count":0},{"offset":27639.518536992902,"char_count":3},{"offset":27899.20830588626,"char_count":5},{"offset":28089.1306741814,"char_count":4},{"offset":28352.696409774657,"char_count":3},{"offset":28620.138112067816,"char_count":3},{"offset":28848.820147361967,"char_count":5}]},{"text":"","ticks":29772,"offset":28848.820147361967,"event_offsets":[{"offset":28848.820147361967,"char_count":0}]},{"text":"when I look back on these days ","ticks":29772,"offset":28848.820147361967,"event_offsets":[{"offset":28848.820147361967,"char_count":0},{"offset":31151.144367103065,"char_count":5},{"offset":31391.454302496917,"char_count":2},{"offset":31627.88827119087,"char_count":5},{"offset":32108.508141978575,"char_count":5},{"offset":32577.500112666574,"char_count":3},{"offset":32802.30618126082,"char_count":6},{"offset":33042.61611665467,"char_count":5}]},{"text":"","ticks":34100,"offset":33042.61611665467,"event_offsets":[{"offset":33042.61611665467,"char_count":0}]},{"text":"I look and see your face ","ticks":34100,"offset":33042.61611665467,"event_offsets":[{"offset":33042.61611665467,"char_count":0},{"offset":34391.45252822017,"char_count":2},{"offset":34860.44449890817,"char_count":5},{"offset":35810.056340383875,"char_count":4},{"offset":36046.49030907783,"char_count":4},{"offset":36744.16431505998,"char_count":5},{"offset":37007.730050653234,"char_count":5}]},{"text":"","ticks":38192,"offset":37007.730050653234,"event_offsets":[{"offset":37007.730050653234,"char_count":0}]},{"text":"you're right there for me. ","ticks":38192,"offset":37007.730050653234,"event_offsets":[{"offset":37007.730050653234,"char_count":0},{"offset":39034.86063470138,"char_count":3},{"offset":39259.666703295625,"char_count":4},{"offset":39499.97663868948,"char_count":6},{"offset":39992.224409576884,"char_count":6},{"offset":40453.46444686509,"char_count":4},{"offset":40720.90614915825,"char_count":4}]},{"text":"","ticks":42024,"offset":40720.90614915825,"event_offsets":[{"offset":40720.90614915825,"char_count":0}]},{"text":"In my dreams I always see you ","ticks":42024,"offset":40720.90614915825,"event_offsets":[{"offset":40720.90614915825,"char_count":0},{"offset":46507.7244321102,"char_count":3},{"offset":46763.538234303654,"char_count":3},{"offset":46968.9644693984,"char_count":7},{"offset":47189.894571292745,"char_count":2},{"offset":47422.4525732868,"char_count":2},{"offset":47895.320510674705,"char_count":5},{"offset":48360.436514662804,"char_count":4},{"offset":48817.800585251105,"char_count":4}]},{"text":"","ticks":50380,"offset":48817.800585251105,"event_offsets":[{"offset":48817.800585251105,"char_count":0}]},{"text":"sore above the sky ","ticks":50380,"offset":48817.800585251105,"event_offsets":[{"offset":48817.800585251105,"char_count":0},{"offset":49282.916589239205,"char_count":5},{"offset":49744.1566265274,"char_count":1},{"offset":49965.08672842175,"char_count":5},{"offset":50465.08643270896,"char_count":4},{"offset":50693.76846800311,"char_count":4}]},{"text":"","ticks":52316,"offset":50693.76846800311,"event_offsets":[{"offset":50693.76846800311,"char_count":0}]},{"text":"in my heart there'll always be ","ticks":52316,"offset":50693.76846800311,"event_offsets":[{"offset":50693.76846800311,"char_count":0},{"offset":53934.076629120216,"char_count":3},{"offset":54220.89816491288,"char_count":3},{"offset":54422.44843330772,"char_count":6},{"offset":54635.626601802265,"char_count":9},{"offset":54903.068304095425,"char_count":2},{"offset":55352.68044128392,"char_count":5},{"offset":55806.16854517232,"char_count":3}]},{"text":"","ticks":57592,"offset":55806.16854517232,"event_offsets":[{"offset":55806.16854517232,"char_count":0}]},{"text":"a place for you ","ticks":57592,"offset":55806.16854517232,"event_offsets":[{"offset":55806.16854517232,"char_count":0},{"offset":56290.664382659925,"char_count":2},{"offset":56771.28425344763,"char_count":6},{"offset":57197.64059043672,"char_count":4},{"offset":57422.44665903097,"char_count":4}]},{"text":"","ticks":59260,"offset":57422.44665903097,"event_offsets":[{"offset":57422.44665903097,"char_count":0}]},{"text":"for all my life ","ticks":59260,"offset":57422.44665903097,"event_offsets":[{"offset":57422.44665903097,"char_count":0},{"offset":58127.87259841293,"char_count":4},{"offset":58364.306567106876,"char_count":4},{"offset":59050.35267298933,"char_count":3},{"offset":59271.28277488367,"char_count":5}]},{"text":"","ticks":61168,"offset":59271.28277488367,"event_offsets":[{"offset":59271.28277488367,"char_count":0}]},{"text":"I'll keep a part of you with me ","ticks":61168,"offset":59271.28277488367,"event_offsets":[{"offset":59271.28277488367,"char_count":0},{"offset":61399.18849312924,"char_count":5},{"offset":61848.80063031773,"char_count":5},{"offset":63248.024608981934,"char_count":2},{"offset":63701.51271287033,"char_count":5},{"offset":64670.50438784555,"char_count":3},{"offset":64914.690289939295,"char_count":4},{"offset":65771.27893061738,"char_count":5},{"offset":66046.47256631035,"char_count":3}]},{"text":"","ticks":68160,"offset":66046.47256631035,"event_offsets":[{"offset":66046.47256631035,"char_count":0}]},{"text":"and everywhere I end there you'll be ","ticks":68160,"offset":66046.47256631035,"event_offsets":[{"offset":66046.47256631035,"char_count":0},{"offset":67654.9987467692,"char_count":4},{"offset":67903.06061556285,"char_count":3},{"offset":68383.68048635055,"char_count":2},{"offset":68596.8586548451,"char_count":6},{"offset":69275.15282732775,"char_count":2},{"offset":69488.3309958223,"char_count":4},{"offset":70213.13676870374,"char_count":6},{"offset":70666.62487259215,"char_count":7},{"offset":71158.87264347955,"char_count":3}]},{"text":"","ticks":73436,"offset":71158.87264347955,"event_offsets":[{"offset":71158.87264347955,"char_count":0}]},{"text":"And everywhere I end there you'll be ","ticks":73436,"offset":71158.87264347955,"event_offsets":[{"offset":71158.87264347955,"char_count":0},{"offset":75123.98657747812,"char_count":4},{"offset":75368.17247957186,"char_count":3},{"offset":75829.41251686007,"char_count":2},{"offset":76058.09455215422,"char_count":6},{"offset":76740.26469133676,"char_count":2},{"offset":76984.45059343052,"char_count":4},{"offset":77666.62073261307,"char_count":6},{"offset":78151.11657010067,"char_count":7},{"offset":78635.61240758828,"char_count":3}]},{"text":"","ticks":81152,"offset":78635.61240758828,"event_offsets":[{"offset":78635.61240758828,"char_count":0}]},{"text":"Will you show me how it feels ","ticks":81152,"offset":78635.61240758828,"event_offsets":[{"offset":78635.61240758828,"char_count":0},{"offset":84174.36882174658,"char_count":5},{"offset":84403.05085704073,"char_count":4},{"offset":84693.74835953329,"char_count":5},{"offset":85092.97292962308,"char_count":3},{"offset":85565.84086701098,"char_count":4},{"offset":85794.52290230514,"char_count":3},{"offset":86065.84057129819,"char_count":6}]},{"text":"","ticks":88820,"offset":86065.84057129819,"event_offsets":[{"offset":86065.84057129819,"char_count":0}]},{"text":"to feel the sky within my reach ","ticks":88820,"offset":86065.84057129819,"event_offsets":[{"offset":86065.84057129819,"char_count":0},{"offset":87674.36675175704,"char_count":3},{"offset":87926.30458725059,"char_count":5},{"offset":88135.60678904524,"char_count":4},{"offset":88410.8004247382,"char_count":4},{"offset":88879.79239542621,"char_count":4},{"offset":89127.85426421986,"char_count":3},{"offset":89724.75313600458,"char_count":3},{"offset":89957.31113799864,"char_count":6}]},{"text":"","ticks":92836,"offset":89957.31113799864,"event_offsets":[{"offset":89957.31113799864,"char_count":0}]},{"text":"and I always will remember ","ticks":92836,"offset":89957.31113799864,"event_offsets":[{"offset":89957.31113799864,"char_count":0},{"offset":91616.22488555619,"char_count":4},{"offset":91860.41078764995,"char_count":2},{"offset":92127.8524899431,"char_count":2},{"offset":92577.4646271316,"char_count":5},{"offset":92810.02262912565,"char_count":5},{"offset":93457.3090680091,"char_count":2},{"offset":93724.75077030226,"char_count":3},{"offset":94418.5488095845,"char_count":4}]},{"text":"","ticks":97440,"offset":94418.5488095845,"event_offsets":[{"offset":94418.5488095845,"char_count":0}]},{"text":"all the strengths you gave to me ","ticks":97440,"offset":94418.5488095845,"event_offsets":[{"offset":94418.5488095845,"char_count":0},{"offset":94666.61067837816,"char_count":4},{"offset":95581.33881955476,"char_count":4},{"offset":95813.89682154881,"char_count":10},{"offset":96294.51669233652,"char_count":4},{"offset":96515.44679423085,"char_count":5},{"offset":96996.06666501856,"char_count":3},{"offset":97228.62466701261,"char_count":3}]},{"text":"","ticks":100340,"offset":97228.62466701261,"event_offsets":[{"offset":97228.62466701261,"char_count":0}]},{"text":"Your love made me make it through ","ticks":100340,"offset":97228.62466701261,"event_offsets":[{"offset":97228.62466701261,"char_count":0},{"offset":99069.70884946552,"char_count":5},{"offset":99294.51491805977,"char_count":5},{"offset":99530.94888675371,"char_count":5},{"offset":99957.3052237428,"char_count":3},{"offset":100189.86322573686,"char_count":5},{"offset":100674.35906322446,"char_count":3},{"offset":100914.66899861832,"char_count":8}]},{"text":"","ticks":104144,"offset":100914.66899861832,"event_offsets":[{"offset":100914.66899861832,"char_count":0}]},{"text":"oh I owe so much to you ","ticks":104144,"offset":100914.66899861832,"event_offsets":[{"offset":100914.66899861832,"char_count":0},{"offset":101740.2499056972,"char_count":3},{"offset":102976.68328296556,"char_count":2},{"offset":103251.87691865853,"char_count":4},{"offset":103736.37275614613,"char_count":3},{"offset":103949.55092464067,"char_count":5},{"offset":104426.29482872848,"char_count":3},{"offset":104670.48073082224,"char_count":4}]},{"text":"","ticks":108020,"offset":104670.48073082224,"event_offsets":[{"offset":104670.48073082224,"char_count":0}]},{"text":"you're right there for me ","ticks":108020,"offset":104670.48073082224,"event_offsets":[{"offset":104670.48073082224,"char_count":0},{"offset":106926.29335016452,"char_count":3},{"offset":107162.72731885847,"char_count":4},{"offset":107418.54112105192,"char_count":6},{"offset":107895.28502513973,"char_count":6},{"offset":108387.53279602714,"char_count":4},{"offset":108608.46289792149,"char_count":3}]},{"text":"","ticks":112084,"offset":108608.46289792149,"event_offsets":[{"offset":108608.46289792149,"char_count":0}]},{"text":"In my dreams I always see ","ticks":112084,"offset":108608.46289792149,"event_offsets":[{"offset":108608.46289792149,"char_count":0},{"offset":114414.66101437295,"char_count":3},{"offset":114670.4748165664,"char_count":3},{"offset":114875.90105166115,"char_count":7},{"offset":115096.8311535555,"char_count":2},{"offset":115329.38915554955,"char_count":2},{"offset":115802.25709293745,"char_count":5},{"offset":116267.37309692556,"char_count":4}]},{"text":"","ticks":119988,"offset":116267.37309692556,"event_offsets":[{"offset":116267.37309692556,"char_count":0}]},{"text":"you sore above the sky ","ticks":119988,"offset":116267.37309692556,"event_offsets":[{"offset":116267.37309692556,"char_count":0},{"offset":116724.73716751386,"char_count":4},{"offset":117189.85317150195,"char_count":5},{"offset":117651.09320879015,"char_count":1},{"offset":117872.0233106845,"char_count":5},{"offset":118372.02301497171,"char_count":4},{"offset":118600.70505026585,"char_count":4}]},{"text":"","ticks":122396,"offset":118600.70505026585,"event_offsets":[{"offset":118600.70505026585,"char_count":0}]},{"text":"in my heart there'll always be ","ticks":122396,"offset":118600.70505026585,"event_offsets":[{"offset":118600.70505026585,"char_count":0},{"offset":121841.01321138296,"char_count":3},{"offset":122127.83474717563,"char_count":3},{"offset":122329.38501557047,"char_count":6},{"offset":122542.56318406502,"char_count":9},{"offset":122810.00488635818,"char_count":2},{"offset":123259.61702354667,"char_count":5},{"offset":123713.10512743506,"char_count":3}]},{"text":"","ticks":127672,"offset":123713.10512743506,"event_offsets":[{"offset":123713.10512743506,"char_count":0}]},{"text":"a place for you ","ticks":127672,"offset":123713.10512743506,"event_offsets":[{"offset":123713.10512743506,"char_count":0},{"offset":124197.60096492268,"char_count":2},{"offset":124678.22083571038,"char_count":6},{"offset":125104.57717269947,"char_count":4},{"offset":125329.38324129372,"char_count":4}]},{"text":"","ticks":129340,"offset":125329.38324129372,"event_offsets":[{"offset":125329.38324129372,"char_count":0}]},{"text":"for all my life ","ticks":129340,"offset":125329.38324129372,"event_offsets":[{"offset":125329.38324129372,"char_count":0},{"offset":126034.80918067567,"char_count":4},{"offset":126271.24314936962,"char_count":4},{"offset":126957.28925525206,"char_count":3},{"offset":127178.21935714642,"char_count":5}]},{"text":"","ticks":131248,"offset":127178.21935714642,"event_offsets":[{"offset":127178.21935714642,"char_count":0}]},{"text":"I'll keep a part of you with me ","ticks":131248,"offset":127178.21935714642,"event_offsets":[{"offset":127178.21935714642,"char_count":0},{"offset":129306.12507539199,"char_count":5},{"offset":129755.73721258048,"char_count":5},{"offset":131154.96119124469,"char_count":2},{"offset":131608.4492951331,"char_count":5},{"offset":132577.4409701083,"char_count":3},{"offset":132821.62687220203,"char_count":4},{"offset":133678.21551288012,"char_count":5},{"offset":133953.4091485731,"char_count":3}]},{"text":"","ticks":138240,"offset":133953.4091485731,"event_offsets":[{"offset":133953.4091485731,"char_count":0}]},{"text":"and everywhere I end there you'll be ","ticks":138240,"offset":133953.4091485731,"event_offsets":[{"offset":133953.4091485731,"char_count":0},{"offset":135561.93532903193,"char_count":4},{"offset":135809.9971978256,"char_count":3},{"offset":136290.6170686133,"char_count":2},{"offset":136503.79523710784,"char_count":6},{"offset":137182.0894095905,"char_count":2},{"offset":137395.26757808504,"char_count":4},{"offset":138120.0733509665,"char_count":6},{"offset":138573.5614548549,"char_count":7},{"offset":139065.8092257423,"char_count":3}]},{"text":"","ticks":143516,"offset":139065.8092257423,"event_offsets":[{"offset":139065.8092257423,"char_count":0}]},{"text":"'Cause I always saw in you ","ticks":143516,"offset":139065.8092257423,"event_offsets":[{"offset":139065.8092257423,"char_count":0},{"offset":140472.78513780632,"char_count":7},{"offset":140689.83927300075,"char_count":2},{"offset":140918.5213082949,"char_count":2},{"offset":141139.45141018924,"char_count":5},{"offset":141372.0094121833,"char_count":4},{"offset":141829.3734827716,"char_count":3},{"offset":142065.80745146555,"char_count":4}]},{"text":"","ticks":146612,"offset":142065.80745146555,"event_offsets":[{"offset":142065.80745146555,"char_count":0}]},{"text":"my light my strength ","ticks":146612,"offset":142065.80745146555,"event_offsets":[{"offset":142065.80745146555,"char_count":0},{"offset":142515.41958865404,"char_count":3},{"offset":143038.67509314066,"char_count":6},{"offset":144205.34106981082,"char_count":3},{"offset":145127.8211443872,"char_count":9}]},{"text":"","ticks":149772,"offset":145127.8211443872,"event_offsets":[{"offset":145127.8211443872,"char_count":0}]},{"text":"and I wanna thank you now ","ticks":149772,"offset":145127.8211443872,"event_offsets":[{"offset":145127.8211443872,"char_count":0},{"offset":147914.64120161592,"char_count":4},{"offset":148143.32323691007,"char_count":2},{"offset":148379.75720560402,"char_count":3},{"offset":148604.56327419827,"char_count":3},{"offset":148856.50110969183,"char_count":6},{"offset":149286.73341338083,"char_count":4},{"offset":149550.29914897407,"char_count":4}]},{"text":"","ticks":154336,"offset":149550.29914897407,"event_offsets":[{"offset":149550.29914897407,"char_count":0}]},{"text":"for all the ways ","ticks":154336,"offset":149550.29914897407,"event_offsets":[{"offset":149550.29914897407,"char_count":0},{"offset":149984.40741936298,"char_count":4},{"offset":150685.95739204503,"char_count":4},{"offset":151658.82503372015,"char_count":4},{"offset":152577.42914159663,"char_count":5}]},{"text":"","ticks":157460,"offset":152577.42914159663,"event_offsets":[{"offset":152577.42914159663,"char_count":0}]},{"text":"you are right there for me ","ticks":157460,"offset":152577.42914159663,"event_offsets":[{"offset":152577.42914159663,"char_count":0},{"offset":154414.63735734962,"char_count":4},{"offset":154647.1953593437,"char_count":4},{"offset":154910.76109493696,"char_count":6},{"offset":155379.75306562494,"char_count":6},{"offset":155829.36520281344,"char_count":4},{"offset":156061.9232048075,"char_count":3}]},{"text":"","ticks":161056,"offset":156061.9232048075,"event_offsets":[{"offset":156061.9232048075,"char_count":0}]},{"text":"you are right there for me ","ticks":161056,"offset":156061.9232048075,"event_offsets":[{"offset":156061.9232048075,"char_count":0},{"offset":158131.68942255454,"char_count":4},{"offset":158360.3714578487,"char_count":4},{"offset":158604.55735994244,"char_count":6},{"offset":159096.80513082986,"char_count":6},{"offset":159546.41726801835,"char_count":4},{"offset":160030.91310550596,"char_count":3}]},{"text":"","ticks":165152,"offset":160030.91310550596,"event_offsets":[{"offset":160030.91310550596,"char_count":0}]},{"text":"Always ","ticks":165152,"offset":160030.91310550596,"event_offsets":[{"offset":160030.91310550596,"char_count":0},{"offset":161817.73375416023,"char_count":2},{"offset":164631.68557828825,"char_count":5}]},{"text":"","ticks":169900,"offset":164631.68557828825,"event_offsets":[{"offset":164631.68557828825,"char_count":0}]},{"text":"In my dreams I always see you ","ticks":169900,"offset":164631.68557828825,"event_offsets":[{"offset":164631.68557828825,"char_count":0},{"offset":166507.65346104026,"char_count":3},{"offset":166763.4672632337,"char_count":3},{"offset":166968.89349832846,"char_count":7},{"offset":167189.82360022282,"char_count":2},{"offset":167422.38160221686,"char_count":2},{"offset":167895.24953960476,"char_count":5},{"offset":168360.36554359287,"char_count":4},{"offset":168817.72961418115,"char_count":4}]},{"text":"","ticks":174220,"offset":168817.72961418115,"event_offsets":[{"offset":168817.72961418115,"char_count":0}]},{"text":"sore above the sky ","ticks":174220,"offset":168817.72961418115,"event_offsets":[{"offset":168817.72961418115,"char_count":0},{"offset":169282.84561816926,"char_count":5},{"offset":169744.08565545746,"char_count":1},{"offset":169965.01575735182,"char_count":5},{"offset":170465.015461639,"char_count":4},{"offset":170693.69749693316,"char_count":4}]},{"text":"","ticks":176156,"offset":170693.69749693316,"event_offsets":[{"offset":170693.69749693316,"char_count":0}]},{"text":"in my heart there'll always be ","ticks":176156,"offset":170693.69749693316,"event_offsets":[{"offset":170693.69749693316,"char_count":0},{"offset":173934.00565805027,"char_count":3},{"offset":174220.82719384294,"char_count":3},{"offset":174422.37746223778,"char_count":6},{"offset":174635.55563073233,"char_count":9},{"offset":174902.99733302547,"char_count":2},{"offset":175352.60947021397,"char_count":5},{"offset":175806.09757410237,"char_count":3}]},{"text":"","ticks":181432,"offset":175806.09757410237,"event_offsets":[{"offset":175806.09757410237,"char_count":0}]},{"text":"a place for you ","ticks":181432,"offset":175806.09757410237,"event_offsets":[{"offset":175806.09757410237,"char_count":0},{"offset":176290.59341158997,"char_count":2},{"offset":176771.2132823777,"char_count":6},{"offset":177197.56961936678,"char_count":4},{"offset":177422.37568796103,"char_count":4}]},{"text":"","ticks":183100,"offset":177422.37568796103,"event_offsets":[{"offset":177422.37568796103,"char_count":0}]},{"text":"for all my life ","ticks":183100,"offset":177422.37568796103,"event_offsets":[{"offset":177422.37568796103,"char_count":0},{"offset":178127.801627343,"char_count":4},{"offset":178364.23559603695,"char_count":4},{"offset":179050.2817019194,"char_count":3},{"offset":179271.21180381373,"char_count":5}]},{"text":"","ticks":185008,"offset":179271.21180381373,"event_offsets":[{"offset":179271.21180381373,"char_count":0}]},{"text":"I'll keep a part of you with me ","ticks":185008,"offset":179271.21180381373,"event_offsets":[{"offset":179271.21180381373,"char_count":0},{"offset":181399.1175220593,"char_count":5},{"offset":181848.7296592478,"char_count":5},{"offset":183247.953637912,"char_count":2},{"offset":183701.4417418004,"char_count":5},{"offset":184670.4334167756,"char_count":3},{"offset":184914.61931886937,"char_count":4},{"offset":185771.20795954744,"char_count":5},{"offset":186046.4015952404,"char_count":3}]},{"text":"","ticks":192000,"offset":186046.4015952404,"event_offsets":[{"offset":186046.4015952404,"char_count":0}]},{"text":"and everywhere I end there you'll be ","ticks":192000,"offset":186046.4015952404,"event_offsets":[{"offset":186046.4015952404,"char_count":0},{"offset":187654.92777569927,"char_count":4},{"offset":187902.98964449292,"char_count":3},{"offset":188383.6095152806,"char_count":2},{"offset":188596.78768377515,"char_count":6},{"offset":189275.0818562578,"char_count":2},{"offset":189488.26002475235,"char_count":4},{"offset":190213.0657976338,"char_count":6},{"offset":190666.55390152222,"char_count":7},{"offset":191158.8016724096,"char_count":3}]},{"text":"","ticks":197276,"offset":191158.8016724096,"event_offsets":[{"offset":191158.8016724096,"char_count":0}]},{"text":"And everywhere I end there you'll be ","ticks":197276,"offset":191158.8016724096,"event_offsets":[{"offset":191158.8016724096,"char_count":0},{"offset":195123.91560640818,"char_count":4},{"offset":195368.10150850192,"char_count":3},{"offset":195829.34154579014,"char_count":2},{"offset":196058.02358108427,"char_count":6},{"offset":196740.19372026683,"char_count":2},{"offset":196984.37962236058,"char_count":4},{"offset":197666.54976154314,"char_count":6},{"offset":198151.04559903074,"char_count":7},{"offset":198635.54143651834,"char_count":3}]},{"text":"","ticks":204992,"offset":198635.54143651834,"event_offsets":[{"offset":198635.54143651834,"char_count":0}]},{"text":"There you'll be... ","ticks":204992,"offset":198635.54143651834,"event_offsets":[{"offset":198635.54143651834,"char_count":0},{"offset":202906.85673980907,"char_count":6},{"offset":205306.0801270477,"char_count":7},{"offset":206030.88589992916,"char_count":6}]},{"text":"","ticks":212624,"offset":206030.88589992916,"event_offsets":[{"offset":206030.88589992916,"char_count":0}]},{"text":"","ticks":212624,"offset":206030.88589992916,"event_offsets":[{"offset":206030.88589992916,"char_count":0}]}]